jicimagelib
